hexer/__init__.py
hexer/regs.py
hexer/test.py
hexer_hx-0.0.2.dist-info/LICENSE
hexer_hx-0.0.2.dist-info/METADATA
hexer_hx-0.0.2.dist-info/WHEEL
hexer_hx-0.0.2.dist-info/entry_points.txt
hexer_hx-0.0.2.dist-info/top_level.txt
hexer_hx-0.0.2.dist-info/RECORD
