Metadata-Version: 2.1
Name: hexer-hx
Version: 0.0.2
Summary: a tool to help in the arcane arts of decoding and reverse engineering binary data
Home-page: https://gitlab.com/hexer-py/hexer
Author: Martin Hultén-Ashauer
Author-email: hexer-info@nimdraug.com
License: MIT
Platform: UNKNOWN
Classifier: Programming Language :: Python :: 3
Classifier: License :: OSI Approved :: MIT License
Classifier: Operating System :: OS Independent
Classifier: Development Status :: 3 - Alpha
Classifier: Intended Audience :: Developers
Classifier: Intended Audience :: Education
Classifier: Intended Audience :: Science/Research
Classifier: Intended Audience :: System Administrators
Classifier: Intended Audience :: Telecommunications Industry
Classifier: Topic :: Text Processing :: Markup
Classifier: Topic :: Scientific/Engineering :: Information Analysis
Classifier: Topic :: Utilities
License-File: LICENSE
